README.rst
setup.py
cellSNP/__init__.py
cellSNP/cellSNP.py
cellSNP/sparseVCF.py
cellSNP/version.py
cellSNP.egg-info/PKG-INFO
cellSNP.egg-info/SOURCES.txt
cellSNP.egg-info/dependency_links.txt
cellSNP.egg-info/entry_points.txt
cellSNP.egg-info/requires.txt
cellSNP.egg-info/top_level.txt
cellSNP/utils/__init__.py
cellSNP/utils/base_utils.py
cellSNP/utils/cellsnp_utils.py
cellSNP/utils/pileup_regions.py
cellSNP/utils/pileup_utils.py
cellSNP/utils/vcf_utils.py