Metadata-Version: 1.0
Name: cellSNP
Version: 0.3.2
Summary: cellSNP - Analysis of expressed alleles in single cells
Home-page: https://github.com/huangyh09/cellSNP
Author: Yuanhua Huang
Author-email: yuanhua@ebi.ac.uk
License: Apache-2.0
Keywords: allelic expression,single-cell RNA-seq
Platform: UNKNOWN
